wagtail_draftail_hovercard/__init__.py
wagtail_draftail_hovercard/forms.py
wagtail_draftail_hovercard/handlers.py
wagtail_draftail_hovercard/static/wagtail_draftail_hovercard/wagtail-draftail-hovercard.js
wagtail_draftail_hovercard/templates/wagtail_draftail_hovercard/modal.html
wagtail_draftail_hovercard/views.py
wagtail_draftail_hovercard/wagtail_hooks.py
wagtail_draftail_hovercard-0.1.0.dist-info/LICENSE
wagtail_draftail_hovercard-0.1.0.dist-info/METADATA
wagtail_draftail_hovercard-0.1.0.dist-info/WHEEL
wagtail_draftail_hovercard-0.1.0.dist-info/RECORD
