Metadata-Version: 2.1
Name: wagtail-draftail-hovercard
Version: 0.1.0
Summary: Hovercard entity for Wagtail's Draftail rich text editor
License: MIT
Keywords: wagtail,draftail,rich text,editor
Author: Storm B. Heg
Author-email: storm@stormbase.digital
Requires-Python: >=3.8,<4.0
Classifier: Environment :: Web Environment
Classifier: Framework :: Wagtail
Classifier: Framework :: Wagtail :: 4
Classifier: Framework :: Wagtail :: 5
Classifier: License :: OSI Approved :: MIT License
Classifier: Programming Language :: Python :: 3
Classifier: Programming Language :: Python :: 3.8
Classifier: Programming Language :: Python :: 3.9
Classifier: Programming Language :: Python :: 3.10
Classifier: Programming Language :: Python :: 3.11
Classifier: Programming Language :: Python :: 3.12
Requires-Dist: wagtail (>=4.2)
Project-URL: changelog, https://github.com/Stormbase/wagtail-draftail-hovercard/blob/main/CHANGELOG.md
Project-URL: repository, https://github.com/Stormbase/wagtail-draftail-hovercard
